zhijie_toolbox/__init__.py
zhijie_toolbox/toolbox.py
zhijie_toolbox-0.1.7.dist-info/LICENSE
zhijie_toolbox-0.1.7.dist-info/METADATA
zhijie_toolbox-0.1.7.dist-info/WHEEL
zhijie_toolbox-0.1.7.dist-info/top_level.txt
zhijie_toolbox-0.1.7.dist-info/RECORD
