Metadata-Version: 2.1
Name: zhijie-toolbox
Version: 0.1.7
Summary: A customized toolbox
Author-email: Zhijie He <zhijiehe97@gmail.com>
Project-URL: Homepage, https://github.com/Zhijie-He/toolbox
Project-URL: Bug Tracker, https://github.com/Zhijie-He/toolbox/issues
Classifier: Programming Language :: Python :: 3
Classifier: License :: OSI Approved :: MIT License
Classifier: Operating System :: OS Independent
Requires-Python: >=3.7
License-File: LICENSE
